gs_api_client/__init__.py
gs_api_client/asynchronous/__init__.py
gs_api_client/asynchronous/api.py
gs_api_client/asynchronous/client.py
gs_api_client/asynchronous/dispatch.py
gs_api_client/asynchronous/method.py
gs_api_client/base/__init__.py
gs_api_client/base/api.py
gs_api_client/base/api_registry.py
gs_api_client/base/client.py
gs_api_client/base/constants.py
gs_api_client/base/dispatch.py
gs_api_client/base/error.py
gs_api_client/base/method.py
gs_api_client/swagger/__init__.py
gs_api_client/swagger/api_client.py
gs_api_client/swagger/configuration.py
gs_api_client/swagger/rest.py
gs_api_client/swagger/api/__init__.py
gs_api_client/swagger/api/certificate_api.py
gs_api_client/swagger/api/deleted_api.py
gs_api_client/swagger/api/events_api.py
gs_api_client/swagger/api/firewall_api.py
gs_api_client/swagger/api/ip_api.py
gs_api_client/swagger/api/iso_image_api.py
gs_api_client/swagger/api/label_api.py
gs_api_client/swagger/api/loadbalancer_api.py
gs_api_client/swagger/api/location_api.py
gs_api_client/swagger/api/marketplace_application_api.py
gs_api_client/swagger/api/network_api.py
gs_api_client/swagger/api/object_storage_api.py
gs_api_client/swagger/api/paas_api.py
gs_api_client/swagger/api/request_api.py
gs_api_client/swagger/api/security_zone_api.py
gs_api_client/swagger/api/server_api.py
gs_api_client/swagger/api/server_ip_api.py
gs_api_client/swagger/api/server_isoimages_api.py
gs_api_client/swagger/api/server_network_api.py
gs_api_client/swagger/api/server_power_api.py
gs_api_client/swagger/api/server_storage_api.py
gs_api_client/swagger/api/ssh_key_api.py
gs_api_client/swagger/api/storage_api.py
gs_api_client/swagger/api/storage_backup_schedule_api.py
gs_api_client/swagger/api/storage_backups_api.py
gs_api_client/swagger/api/storage_snapshot_api.py
gs_api_client/swagger/api/storage_snapshot_schedule_api.py
gs_api_client/swagger/api/template_api.py
gs_api_client/swagger/api/usage_api.py
gs_api_client/swagger/models/__init__.py
gs_api_client-2.2.1.dist-info/LICENSE.md
gs_api_client-2.2.1.dist-info/METADATA
gs_api_client-2.2.1.dist-info/WHEEL
gs_api_client-2.2.1.dist-info/top_level.txt
gs_api_client-2.2.1.dist-info/RECORD
