Metadata-Version: 2.1
Name: gs-api-client
Version: 2.2.1
Summary: Official Python idiomatic client for gridscale services
Home-page: https://github.com/gridscale/gridscale_api_client_python
Author: Thomas Wiebe
Author-email: thomas@gridscale.io
License: MIT
Keywords: API Client
Platform: UNKNOWN
Classifier: Development Status :: 4 - Beta
Classifier: Intended Audience :: Developers
Classifier: License :: OSI Approved :: MIT License
Classifier: Programming Language :: Python :: 3
License-File: LICENSE.md
Requires-Dist: urllib3 (>=1.15)
Requires-Dist: six (>=1.10)
Requires-Dist: certifi
Requires-Dist: python-dateutil
